smart_hass/__init__.py
smart_hass/bayes.py
smart_hass/cli.py
smart_hass/cli_utils.py
smart_hass/multisensor.py
smart_hass/smart_hass.py
smart_hass/templates/bruh_mqtt_multisensor.j2
smart_hass/templates/home_assistant_configuration.j2
smart_hass-0.2.1.dist-info/AUTHORS.md
smart_hass-0.2.1.dist-info/LICENSE
smart_hass-0.2.1.dist-info/METADATA
smart_hass-0.2.1.dist-info/WHEEL
smart_hass-0.2.1.dist-info/entry_points.txt
smart_hass-0.2.1.dist-info/top_level.txt
smart_hass-0.2.1.dist-info/RECORD
