Metadata-Version: 2.1
Name: smart-hass
Version: 0.2.1
Summary: Tools I find useful in my interactions with Home Assistant.
Home-page: https://github.com/jlmcgehee21/smart_hass
Author: Jeff McGehee
Author-email: jlmcgehee21@gmail.com
License: GNU General Public License v3
Keywords: smart_hass
Platform: UNKNOWN
Classifier: Development Status :: 2 - Pre-Alpha
Classifier: Intended Audience :: Developers
Classifier: License :: OSI Approved :: GNU General Public License v3 (GPLv3)
Classifier: Natural Language :: English
Classifier: Programming Language :: Python :: 3
Classifier: Programming Language :: Python :: 3.5
Classifier: Programming Language :: Python :: 3.6
Requires-Dist: Click (>=6.0)
Requires-Dist: PyYAML (>=3.0)
Requires-Dist: Jinja2 (>=2.9.0)
